{"id": 422, "slug": "terraria", "name": "Terraria", "name_original": "Terraria", "description": "<p>Terraria is a 2D action adventure sandbox game, where players create a character and gather resources in order to gradually craft stronger weapons and armor. Players create randomly generated maps that contain different locations within it, and by gathering specific resources and triggering special events, players will fight one of the many in-game bosses. Created characters can be played on different maps.<br />\nThe game introduces hundreds of unique items that can be found across the entirety of the map, some of which may not even be encountered. <br />\nTerraria have many different Biomes and areas with distinct visuals, containing resources and enemies unique to this biome. After gathering materials, players can craft furniture, and build settlements and houses, since after completing events or finding specific items NPCs will start to arrive, and will require player\u2019s protection. Terraria can be played on three difficulties and has a large modding community.</p>", "metacritic": 81, "metacritic_platforms": [{"metascore": 83, "url": "https://www.metacritic.com/game/pc/terraria", "platform": {"platform": 4, "name": "PC", "slug": "pc"}}, {"metascore": 71, "url": "https://www.metacritic.com/game/3ds/terraria", "platform": {"platform": 8, "name": "Nintendo 3DS", "slug": "nintendo-3ds"}}, {"metascore": 82, "url": "https://www.metacritic.com/game/ios/terraria", "platform": {"platform": 3, "name": "iOS", "slug": "ios"}}, {"metascore": 81, "url": "https://www.metacritic.com/game/playstation-3/terraria", "platform": {"platform": 16, "name": "PlayStation 3", "slug": "playstation3"}}, {"metascore": 83, "url": "https://www.metacritic.com/game/playstation-4/terraria", "platform": {"platform": 18, "name": "PlayStation 4", "slug": "playstation4"}}, {"metascore": 85, "url": "https://www.metacritic.com/game/playstation-vita/terraria", "platform": {"platform": 19, "name": "PS Vita", "slug": "ps-vita"}}, {"metascore": 82, "url": "https://www.metacritic.com/game/switch/terraria", "platform": {"platform": 7, "name": "Nintendo Switch", "slug": "nintendo-switch"}}, {"metascore": 81, "url": "https://www.metacritic.com/game/xbox-360/terraria", "platform": {"platform": 14, "name": "Xbox 360", "slug": "xbox360"}}, {"metascore": 84, "url": "https://www.metacritic.com/game/xbox-one/terraria", "platform": {"platform": 1, "name": "Xbox One", "slug": "xbox-one"}}], "released": "2011-05-16", "tba": false, "updated": "2024-04-24T12:26:50", "background_image": "https://media.rawg.io/media/games/f46/f466571d536f2e3ea9e815ad17177501.jpg", "background_image_additional": "https://media.rawg.io/media/screenshots/640/64043c87df0ab807b2f3cb8c3cd48889.jpg", "website": "http://www.terraria.org/", "rating": 4.06, "rating_top": 4, "ratings": [{"id": 4, "title": "recommended", "count": 996, "percent": 42.36}, {"id": 5, "title": "exceptional", "count": 878, "percent": 37.35}, {"id": 3, "title": "meh", "count": 352, "percent": 14.97}, {"id": 1, "title": "skip", "count": 125, "percent": 5.32}], "reactions": {"1": 4, "3": 10, "4": 6, "5": 3, "6": 6, "7": 6, "8": 8, "9": 5, "11": 5, "12": 3}, "added": 12464, "added_by_status": {"yet": 387, "owned": 9176, "beaten": 1193, "toplay": 181, "dropped": 1307, "playing": 220}, "playtime": 15, "screenshots_count": 66, "movies_count": 0, "creators_count": 8, "achievements_count": 377, "parent_achievements_count": 236, "reddit_url": "https://www.reddit.com/r/Terraria/", "reddit_name": "", "reddit_description": "", "reddit_logo": "", "reddit_count": 4094, "twitch_count": 103, "youtube_count": 1000000, "reviews_text_count": 24, "ratings_count": 2327, "suggestions_count": 301, "alternative_names": [], "metacritic_url": "https://www.metacritic.com/game/pc/terraria", "parents_count": 0, "additions_count": 1, "game_series_count": 0, "user_game": null, "reviews_count": 2351, "saturated_color": "0f0f0f", "dominant_color": "0f0f0f", "parent_platforms": [{"platform": {"id": 1, "name": "PC", "slug": "pc"}}, {"platform": {"id": 2, "name": "PlayStation", "slug": "playstation"}}, {"platform": {"id": 3, "name": "Xbox", "slug": "xbox"}}, {"platform": {"id": 4, "name": "iOS", "slug": "ios"}}, {"platform": {"id": 8, "name": "Android", "slug": "android"}}, {"platform": {"id": 5, "name": "Apple Macintosh", "slug": "mac"}}, {"platform": {"id": 6, "name": "Linux", "slug": "linux"}}, {"platform": {"id": 7, "name": "Nintendo", "slug": "nintendo"}}], "platforms": [{"platform": {"id": 14, "name": "Xbox 360", "slug": "xbox360", "image": null, "year_end": null, "year_start": null, "games_count": 2799, "image_background": "https://media.rawg.io/media/games/bc0/bc06a29ceac58652b684deefe7d56099.jpg"}, "released_at": "2011-05-16", "requirements": {}}, {"platform": {"id": 10, "name": "Wii U", "slug": "wii-u", "image": null, "year_end": null, "year_start": null, "games_count": 1127, "image_background": "https://media.rawg.io/media/games/c47/c4796c4c49e7e06ad328e07aa8944cdd.jpg"}, "released_at": "2011-05-16", "requirements": {}}, {"platform": {"id": 8, "name": "Nintendo 3DS", "slug": "nintendo-3ds", "image": null, "year_end": null, "year_start": null, "games_count": 1694, "image_background": "https://media.rawg.io/media/games/89a/89a700d3c6a76bd0610ca89ccd20da54.jpg"}, "released_at": "2011-05-16", "requirements": {}}, {"platform": {"id": 1, "name": "Xbox One", "slug": "xbox-one", "image": null, "year_end": null, "year_start": null, "games_count": 5618, "image_background": "https://media.rawg.io/media/games/310/3106b0e012271c5ffb16497b070be739.jpg"}, "released_at": "2011-05-16", "requirements": {}}, {"platform": {"id": 18, "name": "PlayStation 4", "slug": "playstation4", "image": null, "year_end": null, "year_start": null, "games_count": 6805, "image_background": "https://media.rawg.io/media/games/618/618c2031a07bbff6b4f611f10b6bcdbc.jpg"}, "released_at": "2011-05-16", "requirements": {}}, {"platform": {"id": 3, "name": "iOS", "slug": "ios", "image": null, "year_end": null, "year_start": null, "games_count": 77243, "image_background": "https://media.rawg.io/media/games/942/9424d6bb763dc38d9378b488603c87fa.jpg"}, "released_at": "2011-05-16", "requirements": {"minimum": "iPad 2 Wifi, iPad 2 3G, iPhone 4S, iPad Third Gen, iPad Third Gen 4G, iPhone 5, iPod Touch Fifth Gen, iPad Fourth Gen, iPad Fourth Gen 4G, iPad Mini, iPad Mini 4G, iPhone 5c, iPhone 5s, iPad Air, iPad Air Cellular, iPad Mini Retina, iPad Mini Retina Cellular, iPhone 6, iPhone 6 Plus, iPad Air 2, iPad Air 2 Cellular, iPad Mini 3, iPad Mini 3 Cellular, iPod Touch Sixth Gen, iPhone 6s, iPhone 6s Plus, iPad Mini 4, iPad Mini 4 Cellular, iPad Pro, iPad Pro Cellular, iPad Pro 9.7, iPad Pro 9.7 Cellular, iPhone SE, iPhone 7, iPhone 7 Plus, iPad 6 1 1, iPad 6 1 2, iPad 7 1, iPad 7 2, iPad 7 3, iPad 7 4, iPhone 8, iPhone 8 Plus, iPhone X, iPad 7 5, iPad 7 6, iPhone X S, iPhone X S Max, iPhone X R, iPad 8 1 2, iPad 8 3 4, iPad 8 5 6, iPad 8 7 8, iPad Mini 5, iPad Mini 5 Cellular, iPad Air 3, iPad Air 3 Cellular, iPod Touch Seventh Gen"}}, {"platform": {"id": 4, "name": "PC", "slug": "pc", "image": null, "year_end": null, "year_start": null, "games_count": 528349, "image_background": "https://media.rawg.io/media/games/120/1201a40e4364557b124392ee50317b99.jpg"}, "released_at": "2011-05-16", "requirements": {"minimum": "XP / Vista / 7 / 8 / 10, Processor: 1.6 Ghz, Memory: 2 GB, Hard Disk Space: 1 GB,  Video Card: 128mb Video Memory, capable of Shader Model 1.1, DirectX\u00ae: 9.0c or Greater,Mouse, Keyboard.", "recommended": "7 / 8 / 10Processor: Dual Core 3.0 Ghz Memory: 4GBHard Disk Space: 1 GB  Video Card: 256mb Video Memory, capable of Shader Model 2.0+DirectX\u00ae: 9.0c or Greater"}}, {"platform": {"id": 5, "name": "macOS", "slug": "macos", "image": null, "year_end": null, "year_start": null, "games_count": 103731, "image_background": "https://media.rawg.io/media/games/157/15742f2f67eacff546738e1ab5c19d20.jpg"}, "released_at": "2011-05-16", "requirements": {"minimum": "OS X 10.9.5Processor: 2.0 GhzMemory: 2.5GBHard Disk Space: 200MB  Video Card: 128mb Video Memory, capable of OpenGL 3.0+ support (2.1 with ARB extensions acceptable)", "recommended": "OS X 10.10Processor: Dual Core 3.0 GhzMemory: 4GBHard Disk Space: 200MB  Video Card: 256mb Video Memory, capable of OpenGL 3.0+ support (2.1 with ARB extensions acceptable)"}}, {"platform": {"id": 6, "name": "Linux", "slug": "linux", "image": null, "year_end": null, "year_start": null, "games_count": 76731, "image_background": "https://media.rawg.io/media/games/9fa/9fa63622543e5d4f6d99aa9d73b043de.jpg"}, "released_at": "2011-05-16", "requirements": {"minimum": "Ubuntu 14.04Processor: 2.0 GhzMemory: 2.5GBHard Disk Space: 200MB Video Card: 128mb Video Memory, capable of OpenGL 3.0+ support (2.1 with ARB extensions acceptable)", "recommended": "Ubuntu 14.04 Processor: Dual Core 3.0 GhzMemory: 4GBHard Disk Space: 200MB  Video Card: 256mb Video Memory, capable of OpenGL 3.0+ support (2.1 with ARB extensions acceptable)"}}, {"platform": {"id": 7, "name": "Nintendo Switch", "slug": "nintendo-switch", "image": null, "year_end": null, "year_start": null, "games_count": 5448, "image_background": "https://media.rawg.io/media/games/4cf/4cfc6b7f1850590a4634b08bfab308ab.jpg"}, "released_at": "2011-05-16", "requirements": {}}, {"platform": {"id": 16, "name": "PlayStation 3", "slug": "playstation3", "image": null, "year_end": null, "year_start": null, "games_count": 3165, "image_background": "https://media.rawg.io/media/games/942/9424d6bb763dc38d9378b488603c87fa.jpg"}, "released_at": "2011-05-16", "requirements": {}}, {"platform": {"id": 19, "name": "PS Vita", "slug": "ps-vita", "image": null, "year_end": null, "year_start": null, "games_count": 1447, "image_background": "https://media.rawg.io/media/games/e4f/e4fb3fd188f61fabec48dca22e6ef28a.jpg"}, "released_at": "2011-05-16", "requirements": {}}, {"platform": {"id": 21, "name": "Android", "slug": "android", "image": null, "year_end": null, "year_start": null, "games_count": 52348, "image_background": "https://media.rawg.io/media/games/238/2383a172b4d50a7b44e07980eb7141ea.jpg"}, "released_at": "2011-05-16", "requirements": {"minimum": "4.0.3 and up"}}], "stores": [{"id": 9233, "url": "", "store": {"id": 2, "name": "Xbox Store", "slug": "xbox-store", "domain": "microsoft.com", "games_count": 4847, "image_background": "https://media.rawg.io/media/games/587/587588c64afbff80e6f444eb2e46f9da.jpg"}}, {"id": 11525, "url": "", "store": {"id": 1, "name": "Steam", "slug": "steam", "domain": "store.steampowered.com", "games_count": 91507, "image_background": "https://media.rawg.io/media/games/34b/34b1f1850a1c06fd971bc6ab3ac0ce0e.jpg"}}, {"id": 26244, "url": "", "store": {"id": 5, "name": "GOG", "slug": "gog", "domain": "gog.com", "games_count": 5950, "image_background": "https://media.rawg.io/media/games/ebd/ebdbb7eb52bd58b0e7fa4538d9757b60.jpg"}}, {"id": 28072, "url": "", "store": {"id": 6, "name": "Nintendo Store", "slug": "nintendo", "domain": "nintendo.com", "games_count": 9009, "image_background": "https://media.rawg.io/media/games/1f4/1f47a270b8f241e4676b14d39ec620f7.jpg"}}, {"id": 426, "url": "", "store": {"id": 4, "name": "App Store", "slug": "apple-appstore", "domain": "apps.apple.com", "games_count": 75449, "image_background": "https://media.rawg.io/media/games/f46/f466571d536f2e3ea9e815ad17177501.jpg"}}, {"id": 40558, "url": "", "store": {"id": 8, "name": "Google Play", "slug": "google-play", "domain": "play.google.com", "games_count": 17091, "image_background": "https://media.rawg.io/media/games/198/1988a337305e008b41d7f536ce9b73f6.jpg"}}, {"id": 4127, "url": "", "store": {"id": 3, "name": "PlayStation Store", "slug": "playstation-store", "domain": "store.playstation.com", "games_count": 7935, "image_background": "https://media.rawg.io/media/games/021/021c4e21a1824d2526f925eff6324653.jpg"}}], "developers": [{"id": 2445, "name": "Engine Software", "slug": "engine-software", "games_count": 50, "image_background": "https://media.rawg.io/media/screenshots/936/93693ede28bc35eec0b8ac2a72339647.jpg"}, {"id": 1757, "name": "Codeglue", "slug": "codeglue", "games_count": 10, "image_background": "https://media.rawg.io/media/screenshots/c06/c0684fd165aa95f2b0fd72566d7b076d.jpg"}, {"id": 4066, "name": "Pipeworks Studio", "slug": "pipeworks-studio", "games_count": 5, "image_background": "https://media.rawg.io/media/screenshots/e81/e81dce2619c78b1cc045f078658590b8.jpg"}, {"id": 4512, "name": "Re-Logic", "slug": "re-logic", "games_count": 5, "image_background": "https://media.rawg.io/media/screenshots/600/60061e01c156dfbcdf46d0f1d90ae567.jpg"}], "genres": [{"id": 4, "name": "Action", "slug": "action", "games_count": 179305, "image_background": "https://media.rawg.io/media/games/021/021c4e21a1824d2526f925eff6324653.jpg"}, {"id": 51, "name": "Indie", "slug": "indie", "games_count": 63960, "image_background": "https://media.rawg.io/media/games/095/0953bf01cd4e4dd204aba85489ac9868.jpg"}, {"id": 83, "name": "Platformer", "slug": "platformer", "games_count": 100777, "image_background": "https://media.rawg.io/media/games/f8c/f8c6a262ead4c16b47e1219310210eb3.jpg"}], "tags": [{"id": 31, "name": "Singleplayer", "slug": "singleplayer", "language": "eng", "games_count": 220522, "image_background": "https://media.rawg.io/media/games/511/5118aff5091cb3efec399c808f8c598f.jpg"}, {"id": 40847, "name": "Steam Achievements", "slug": "steam-achievements", "language": "eng", "games_count": 36657, "image_background": "https://media.rawg.io/media/games/490/49016e06ae2103881ff6373248843069.jpg"}, {"id": 7, "name": "Multiplayer", "slug": "multiplayer", "language": "eng", "games_count": 37503, "image_background": "https://media.rawg.io/media/games/b49/b4912b5dbfc7ed8927b65f05b8507f6c.jpg"}, {"id": 40836, "name": "Full controller support", "slug": "full-controller-support", "language": "eng", "games_count": 17269, "image_background": "https://media.rawg.io/media/games/8a0/8a02f84a5916ede2f923b88d5f8217ba.jpg"}, {"id": 40849, "name": "Steam Cloud", "slug": "steam-cloud", "language": "eng", "games_count": 17278, "image_background": "https://media.rawg.io/media/games/b49/b4912b5dbfc7ed8927b65f05b8507f6c.jpg"}, {"id": 13, "name": "Atmospheric", "slug": "atmospheric", "language": "eng", "games_count": 32548, "image_background": "https://media.rawg.io/media/games/f46/f466571d536f2e3ea9e815ad17177501.jpg"}, {"id": 7808, "name": "steam-trading-cards", "slug": "steam-trading-cards", "language": "eng", "games_count": 7569, "image_background": "https://media.rawg.io/media/games/310/3106b0e012271c5ffb16497b070be739.jpg"}, {"id": 24, "name": "RPG", "slug": "rpg", "language": "eng", "games_count": 20341, "image_background": "https://media.rawg.io/media/games/ee3/ee3e10193aafc3230ba1cae426967d10.jpg"}, {"id": 18, "name": "Co-op", "slug": "co-op", "language": "eng", "games_count": 11289, "image_background": "https://media.rawg.io/media/games/d0f/d0f91fe1d92332147e5db74e207cfc7a.jpg"}, {"id": 36, "name": "Open World", "slug": "open-world", "language": "eng", "games_count": 7266, "image_background": "https://media.rawg.io/media/games/511/5118aff5091cb3efec399c808f8c598f.jpg"}, {"id": 45, "name": "2D", "slug": "2d", "language": "eng", "games_count": 194092, "image_background": "https://media.rawg.io/media/games/ffe/ffed87105b14f5beff72ff44a7793fd5.jpg"}, {"id": 9, "name": "Online Co-Op", "slug": "online-co-op", "language": "eng", "games_count": 5356, "image_background": "https://media.rawg.io/media/games/15c/15c95a4915f88a3e89c821526afe05fc.jpg"}, {"id": 6, "name": "Exploration", "slug": "exploration", "language": "eng", "games_count": 22367, "image_background": "https://media.rawg.io/media/games/737/737ea5662211d2e0bbd6f5989189e4f1.jpg"}, {"id": 37, "name": "Sandbox", "slug": "sandbox", "language": "eng", "games_count": 6746, "image_background": "https://media.rawg.io/media/games/849/849414b978db37d4563ff9e4b0d3a787.jpg"}, {"id": 1, "name": "Survival", "slug": "survival", "language": "eng", "games_count": 8457, "image_background": "https://media.rawg.io/media/games/d2c/d2c74dacd89fd817c2deb625b01adb1a.jpg"}, {"id": 397, "name": "Online multiplayer", "slug": "online-multiplayer", "language": "eng", "games_count": 3805, "image_background": "https://media.rawg.io/media/games/fba/fbae1bcfae1feffda6a11fbc1c939420.jpg"}, {"id": 122, "name": "Pixel Graphics", "slug": "pixel-graphics", "language": "eng", "games_count": 93033, "image_background": "https://media.rawg.io/media/screenshots/6fe/6fe228662a253cd929cc78a103541ee0.jpg"}, {"id": 468, "name": "role-playing", "slug": "role-playing", "language": "eng", "games_count": 1567, "image_background": "https://media.rawg.io/media/games/f99/f9979698c43fd84c3ab69280576dd3af.jpg"}, {"id": 107, "name": "Family Friendly", "slug": "family-friendly", "language": "eng", "games_count": 7066, "image_background": "https://media.rawg.io/media/games/6c8/6c8cb4780ce30b76b944cf656e8fff49.jpg"}, {"id": 336, "name": "controller support", "slug": "controller-support", "language": "eng", "games_count": 293, "image_background": "https://media.rawg.io/media/games/942/9424d6bb763dc38d9378b488603c87fa.jpg"}, {"id": 5, "name": "Replay Value", "slug": "replay-value", "language": "eng", "games_count": 1602, "image_background": "https://media.rawg.io/media/games/21c/21cc15d233117c6809ec86870559e105.jpg"}, {"id": 125, "name": "Crafting", "slug": "crafting", "language": "eng", "games_count": 4007, "image_background": "https://media.rawg.io/media/games/283/283e7e600366b0da7021883d27159b27.jpg"}, {"id": 39, "name": "Building", "slug": "building", "language": "eng", "games_count": 5943, "image_background": "https://media.rawg.io/media/games/02f/02f775a806c6cd64c28d5aeca928dc76.jpg"}, {"id": 337, "name": "overlay", "slug": "overlay", "language": "eng", "games_count": 217, "image_background": "https://media.rawg.io/media/games/fad/fadc4be043ed07904012d47cd02671e4.jpg"}], "publishers": [{"id": 243, "name": "505 Games", "slug": "505-games", "games_count": 174, "image_background": "https://media.rawg.io/media/games/fe6/fe68940746007261e34da4d9cce81423.jpg"}, {"id": 180, "name": "Headup Games", "slug": "headup-games", "games_count": 124, "image_background": "https://media.rawg.io/media/screenshots/262/2623a3e832b3cb31186f3d59ea59983f.jpg"}, {"id": 11056, "name": "Spike Chunsoft", "slug": "spike-chunsoft", "games_count": 20, "image_background": "https://media.rawg.io/media/screenshots/efc/efcbfd4aed90a35aaa598465d662f8e1.jpg"}, {"id": 3627, "name": "Re-Logic", "slug": "re-logic", "games_count": 5, "image_background": "https://media.rawg.io/media/screenshots/1c5/1c59faf09d5c71921867679b81d09964.jpg"}], "esrb_rating": {"id": 3, "name": "Teen", "slug": "teen"}, "clip": null, "description_raw": "Terraria is a 2D action adventure sandbox game, where players create a character and gather resources in order to gradually craft stronger weapons and armor. Players create randomly generated maps that contain different locations within it, and by gathering specific resources and triggering special events, players will fight one of the many in-game bosses. Created characters can be played on different maps.\r\nThe game introduces hundreds of unique items that can be found across the entirety of the map, some of which may not even be encountered. \r\nTerraria have many different Biomes and areas with distinct visuals, containing resources and enemies unique to this biome. After gathering materials, players can craft furniture, and build settlements and houses, since after completing events or finding specific items NPCs will start to arrive, and will require player\u2019s protection. Terraria can be played on three difficulties and has a large modding community."}