{"id": 11859, "slug": "team-fortress-2", "name": "Team Fortress 2", "name_original": "Team Fortress 2", "description": "<p>TF2 is an objective based arena shooter with unique characters, representing different classes, acting as a staple of casual and competitive gaming for Steam. Dozens of different maps and game modes are trying to keep this game alive, after all the years it was available. Each character has a vast arsenal that can be accessed through completing in-game achievements, randomly receiving them from loot-boxes within the game, crafting them or just buying and trading items on the Steam Market. <br />\nFor players, that&#39;s not into the direct clash with players from the enemy team, Team Fortress 2 introduced a PvE mode, which is wave defense from the mirrored robotic opponents that have qualities of some of the playable classes. <br />\nEvery update and introduction, made over years, provided a lot of entertainment In the form of comic books an short animated videos, creating and explaining a story behind endless clashes for resources, briefcases or pure domination.</p>", "metacritic": 92, "metacritic_platforms": [], "released": "2007-10-10", "tba": false, "updated": "2024-04-23T21:57:30", "background_image": "https://media.rawg.io/media/games/46d/46d98e6910fbc0706e2948a7cc9b10c5.jpg", "background_image_additional": "https://media.rawg.io/media/screenshots/22d/22d0ef79c8ff037f83c633f904f79198.jpg", "website": "http://www.teamfortress.com/", "rating": 3.68, "rating_top": 4, "ratings": [{"id": 4, "title": "recommended", "count": 1297, "percent": 45.25}, {"id": 3, "title": "meh", "count": 691, "percent": 24.11}, {"id": 5, "title": "exceptional", "count": 600, "percent": 20.94}, {"id": 1, "title": "skip", "count": 278, "percent": 9.7}], "reactions": {"1": 5, "3": 5, "4": 8, "5": 3, "6": 2, "7": 4, "8": 7, "9": 1, "11": 3, "12": 3, "15": 1, "16": 2, "17": 1, "20": 2, "21": 1}, "added": 13122, "added_by_status": {"yet": 186, "owned": 10141, "beaten": 789, "toplay": 46, "dropped": 1792, "playing": 168}, "playtime": 9, "screenshots_count": 10, "movies_count": 0, "creators_count": 3, "achievements_count": 520, "parent_achievements_count": 518, "reddit_url": "https://www.reddit.com/r/tf2/", "reddit_name": "", "reddit_description": "", "reddit_logo": "", "reddit_count": 11838, "twitch_count": 122, "youtube_count": 1000000, "reviews_text_count": 27, "ratings_count": 2839, "suggestions_count": 533, "alternative_names": [], "metacritic_url": "", "parents_count": 0, "additions_count": 1, "game_series_count": 2, "user_game": null, "reviews_count": 2866, "saturated_color": "0f0f0f", "dominant_color": "0f0f0f", "parent_platforms": [{"platform": {"id": 1, "name": "PC", "slug": "pc"}}, {"platform": {"id": 5, "name": "Apple Macintosh", "slug": "mac"}}, {"platform": {"id": 6, "name": "Linux", "slug": "linux"}}], "platforms": [{"platform": {"id": 4, "name": "PC", "slug": "pc", "image": null, "year_end": null, "year_start": null, "games_count": 528349, "image_background": "https://media.rawg.io/media/games/120/1201a40e4364557b124392ee50317b99.jpg"}, "released_at": "2007-10-10", "requirements": {"minimum": "Minimum:\nOS: Windows\u00ae 7 (32/64-bit)/Vista/XP\nProcessor: 1.7 GHz Processor or better\nMemory: 512 MB RAM\nDirectX: Version 8.1\nNetwork: Broadband Internet connection\nStorage: 15 GB available space", "recommended": "Recommended:\nOS: Windows\u00ae 7 (32/64-bit)\nProcessor: Pentium 4 processor (3.0GHz, or better)\nMemory: 1 GB RAM\nDirectX: Version 9.0c\nNetwork: Broadband Internet connection\nStorage: 15 GB available space"}}, {"platform": {"id": 5, "name": "macOS", "slug": "macos", "image": null, "year_end": null, "year_start": null, "games_count": 103731, "image_background": "https://media.rawg.io/media/games/157/15742f2f67eacff546738e1ab5c19d20.jpg"}, "released_at": "2007-10-10", "requirements": {"minimum": "Minimum:\nOS: OS X version Leopard 10.5.8 and above\nProcessor: 1.7 GHz Processor or better\nMemory: 1 GB RAM\nGraphics: NVIDIA GeForce 8 or higher, ATI X1600 or higher, Intel HD 3000 or higher\nNetwork: Broadband Internet connection\nStorage: 15 GB available space"}}, {"platform": {"id": 6, "name": "Linux", "slug": "linux", "image": null, "year_end": null, "year_start": null, "games_count": 76731, "image_background": "https://media.rawg.io/media/games/9fa/9fa63622543e5d4f6d99aa9d73b043de.jpg"}, "released_at": "2007-10-10", "requirements": {"minimum": "Minimum:\nOS: Ubuntu 12.04\nProcessor: Dual core from Intel or AMD at 2.8 GHz\nMemory: 1 GB RAM\nGraphics: nVidia GeForce 8600/9600GT, ATI/AMD Radeon HD2600/3600 (Graphic Drivers: nVidia 310, AMD 12.11), OpenGL 2.1\nNetwork: Broadband Internet connection\nStorage: 15 GB available space\nSound Card: OpenAL Compatible Sound Card"}}], "stores": [{"id": 13018, "url": "", "store": {"id": 1, "name": "Steam", "slug": "steam", "domain": "store.steampowered.com", "games_count": 91507, "image_background": "https://media.rawg.io/media/games/34b/34b1f1850a1c06fd971bc6ab3ac0ce0e.jpg"}}], "developers": [{"id": 1612, "name": "Valve Software", "slug": "valve-software", "games_count": 43, "image_background": "https://media.rawg.io/media/screenshots/d33/d331d95adf10b44ee3678129020bc31f.jpg"}], "genres": [{"id": 4, "name": "Action", "slug": "action", "games_count": 179305, "image_background": "https://media.rawg.io/media/games/021/021c4e21a1824d2526f925eff6324653.jpg"}, {"id": 2, "name": "Shooter", "slug": "shooter", "games_count": 59474, "image_background": "https://media.rawg.io/media/games/26d/26d4437715bee60138dab4a7c8c59c92.jpg"}], "tags": [{"id": 40847, "name": "Steam Achievements", "slug": "steam-achievements", "language": "eng", "games_count": 36657, "image_background": "https://media.rawg.io/media/games/490/49016e06ae2103881ff6373248843069.jpg"}, {"id": 7, "name": "Multiplayer", "slug": "multiplayer", "language": "eng", "games_count": 37503, "image_background": "https://media.rawg.io/media/games/b49/b4912b5dbfc7ed8927b65f05b8507f6c.jpg"}, {"id": 7808, "name": "steam-trading-cards", "slug": "steam-trading-cards", "language": "eng", "games_count": 7569, "image_background": "https://media.rawg.io/media/games/310/3106b0e012271c5ffb16497b070be739.jpg"}, {"id": 18, "name": "Co-op", "slug": "co-op", "language": "eng", "games_count": 11289, "image_background": "https://media.rawg.io/media/games/d0f/d0f91fe1d92332147e5db74e207cfc7a.jpg"}, {"id": 411, "name": "cooperative", "slug": "cooperative", "language": "eng", "games_count": 4818, "image_background": "https://media.rawg.io/media/games/dd5/dd50d4266915d56dd5b63ae1bf72606a.jpg"}, {"id": 8, "name": "First-Person", "slug": "first-person", "language": "eng", "games_count": 31080, "image_background": "https://media.rawg.io/media/games/be0/be01c3d7d8795a45615da139322ca080.jpg"}, {"id": 40845, "name": "Partial Controller Support", "slug": "partial-controller-support", "language": "eng", "games_count": 11441, "image_background": "https://media.rawg.io/media/games/2ad/2ad87a4a69b1104f02435c14c5196095.jpg"}, {"id": 30, "name": "FPS", "slug": "fps", "language": "eng", "games_count": 13046, "image_background": "https://media.rawg.io/media/games/7a2/7a2500ee8b2c0e1ff268bb4479463dea.jpg"}, {"id": 9, "name": "Online Co-Op", "slug": "online-co-op", "language": "eng", "games_count": 5356, "image_background": "https://media.rawg.io/media/games/15c/15c95a4915f88a3e89c821526afe05fc.jpg"}, {"id": 4, "name": "Funny", "slug": "funny", "language": "eng", "games_count": 24439, "image_background": "https://media.rawg.io/media/games/744/744adc36e6573dd67a0cb0e373738d19.jpg"}, {"id": 123, "name": "Comedy", "slug": "comedy", "language": "eng", "games_count": 12144, "image_background": "https://media.rawg.io/media/games/c7a/c7a71a0531a9518236d99d0d60abe447.jpg"}, {"id": 79, "name": "Free to Play", "slug": "free-to-play", "language": "eng", "games_count": 6466, "image_background": "https://media.rawg.io/media/games/095/0953bf01cd4e4dd204aba85489ac9868.jpg"}, {"id": 80, "name": "Tactical", "slug": "tactical", "language": "eng", "games_count": 4935, "image_background": "https://media.rawg.io/media/games/d1f/d1f872a48286b6b751670817d5c1e1be.jpg"}, {"id": 11669, "name": "stats", "slug": "stats", "language": "eng", "games_count": 4884, "image_background": "https://media.rawg.io/media/games/179/179245a3693049a11a25b900ab18f8f7.jpg"}, {"id": 40852, "name": "Steam Workshop", "slug": "steam-workshop", "language": "eng", "games_count": 1466, "image_background": "https://media.rawg.io/media/games/dd5/dd50d4266915d56dd5b63ae1bf72606a.jpg"}, {"id": 40832, "name": "Cross-Platform Multiplayer", "slug": "cross-platform-multiplayer", "language": "eng", "games_count": 2552, "image_background": "https://media.rawg.io/media/games/9f1/9f1891779cb20f44de93cef33b067e50.jpg"}, {"id": 40838, "name": "Includes level editor", "slug": "includes-level-editor", "language": "eng", "games_count": 1840, "image_background": "https://media.rawg.io/media/games/93e/93ee6101e1c943732f06080dddb0fe4c.jpg"}, {"id": 62, "name": "Moddable", "slug": "moddable", "language": "eng", "games_count": 899, "image_background": "https://media.rawg.io/media/games/be9/be9cf02720c9326e11d0fda14518554f.jpg"}, {"id": 40837, "name": "In-App Purchases", "slug": "in-app-purchases", "language": "eng", "games_count": 2510, "image_background": "https://media.rawg.io/media/games/651/651ae84f2d5e36206aad90976a453329.jpg"}, {"id": 40833, "name": "Captions available", "slug": "captions-available", "language": "eng", "games_count": 1322, "image_background": "https://media.rawg.io/media/games/46d/46d98e6910fbc0706e2948a7cc9b10c5.jpg"}, {"id": 125, "name": "Crafting", "slug": "crafting", "language": "eng", "games_count": 4007, "image_background": "https://media.rawg.io/media/games/283/283e7e600366b0da7021883d27159b27.jpg"}, {"id": 11, "name": "Team-Based", "slug": "team-based", "language": "eng", "games_count": 1534, "image_background": "https://media.rawg.io/media/games/8cc/8cce7c0e99dcc43d66c8efd42f9d03e3.jpg"}, {"id": 40856, "name": "Valve Anti-Cheat enabled", "slug": "valve-anti-cheat-enabled", "language": "eng", "games_count": 105, "image_background": "https://media.rawg.io/media/games/78d/78dfae12fb8c5b16cd78648553071e0a.jpg"}, {"id": 170, "name": "Competitive", "slug": "competitive", "language": "eng", "games_count": 1126, "image_background": "https://media.rawg.io/media/games/476/476178ef18ab0534771d099f51cdc694.jpg"}, {"id": 197, "name": "Robots", "slug": "robots", "language": "eng", "games_count": 8134, "image_background": "https://media.rawg.io/media/games/43c/43cfdb7fdc48d99b4a4c2525b411daf8.jpg"}, {"id": 40834, "name": "Commentary available", "slug": "commentary-available", "language": "eng", "games_count": 268, "image_background": "https://media.rawg.io/media/games/be0/be01c3d7d8795a45615da139322ca080.jpg"}, {"id": 164, "name": "Cartoony", "slug": "cartoony", "language": "eng", "games_count": 5248, "image_background": "https://media.rawg.io/media/games/bbe/bbe47995ed6f8b054afa6110f522515d.jpg"}, {"id": 179, "name": "Cartoon", "slug": "cartoon", "language": "eng", "games_count": 5618, "image_background": "https://media.rawg.io/media/games/b44/b448c0725eb490dda9cfb23b826da68a.jpg"}, {"id": 265, "name": "Class-Based", "slug": "class-based", "language": "eng", "games_count": 579, "image_background": "https://media.rawg.io/media/games/737/73727793e477ebf228ecd389f1301fee.jpg"}, {"id": 245, "name": "Trading", "slug": "trading", "language": "eng", "games_count": 1093, "image_background": "https://media.rawg.io/media/screenshots/045/04591a8f99662aa1336d41e6c3c819ad.jpeg"}], "publishers": [{"id": 3399, "name": "Valve", "slug": "valve", "games_count": 46, "image_background": "https://media.rawg.io/media/screenshots/9fd/9fd128fef547eb630182a1995b1edeb5.jpg"}], "esrb_rating": {"id": 4, "name": "Mature", "slug": "mature"}, "clip": null, "description_raw": "TF2 is an objective based arena shooter with unique characters, representing different classes, acting as a staple of casual and competitive gaming for Steam. Dozens of different maps and game modes are trying to keep this game alive, after all the years it was available. Each character has a vast arsenal that can be accessed through completing in-game achievements, randomly receiving them from loot-boxes within the game, crafting them or just buying and trading items on the Steam Market. \r\nFor players, that's not into the direct clash with players from the enemy team, Team Fortress 2 introduced a PvE mode, which is wave defense from the mirrored robotic opponents that have qualities of some of the playable classes. \r\nEvery update and introduction, made over years, provided a lot of entertainment In the form of comic books an short animated videos, creating and explaining a story behind endless clashes for resources, briefcases or pure domination."}